design.sv
// Code your design here
module cache(
  input[7:0] addr,
  input clk, rst,
  output[7:0] out
);
  
  reg[7:0] data_mem[0:7];	// Cache Memory
  reg[5:0] tag[0:7];		// 8-2 = 6 bit, No offset
  reg last_used[0:3];		// 4-sets, 0 if last used is 1
  reg[7:0] op;				// output register
  reg[0:7] valid;			// Valid bit
  reg[7:0] RAM[0:255];		// RAM
  
  integer i;
  
  assign out = op;
  
  initial
    begin
      $dumpfile("dump.vcd");
      $dumpvars(1, cache);
    end
  
  initial
    begin
      for(i=0;i<256;i=i+1)
        RAM[i] = i;
    end
  
  initial
    begin
      for(i=0;i<8;i=i+1)
        begin
          last_used[i/2] = 1;
          tag[i] = 0;
        end
      valid = 0;
      op = 0;      
    end
  
  always @(*)
    begin
      if (rst == 0)
        begin
          for(i=0;i<8;i=i+1)
            begin
              last_used[i/2] = 0;
              tag[i] = 0;
            end
          valid = 0;
          op = 0; 
        end
    end
  
  always @(posedge clk)
    begin
      // HIT
      if (tag[{addr[1:0],1'b0}] == addr[7:2] && valid[{addr[1:0],1'b0}] == 1'b1)
        begin
          op = data_mem[{addr[1:0],1'b0}];
          last_used[addr[1:0]] = 1'b1;
        end
      
      else if(tag[{addr[1:0],1'b1}] == addr[7:2] && valid[{addr[1:0],1'b1}] == 1'b1)
        begin
          op = data_mem[{addr[1:0],1'b1}];
          last_used[addr[1:0]] = 1'b0;
        end
      
      // MISS
      else
        begin
          data_mem[{addr[1:0], last_used[addr[1:0]]}] = RAM[addr];
          op = RAM[addr];
          tag[{addr[1:0], last_used[addr[1:0]]}] = addr[7:2];
          valid[{addr[1:0], last_used[addr[1:0]]}] = 1'b1;
          last_used[addr[1:0]] = ~last_used[addr[1:0]];          
        end
    end
  
endmodule

testbench.sv
module tb;
  
  reg clk, rst;
  reg[7:0] addr;
  wire[7:0] out;
  
  cache c1(.addr(addr),
           .clk(clk),
           .rst(rst),
           .out(out)
          );
  
  always #5 clk=~clk;
  
  initial 
    begin
      clk = 1'b0;
      rst = 1'b0;
      #50
      
      rst=1'b1;
      addr = 8'd22;
      #20
      
      addr = 8'd24;
      #20
      
      addr = 8'd26;
      #20
      
      addr = 8'd22;
      #20
      
      addr = 8'd29;
      #20
      
      addr = 8'd30;
      #20
      
      addr = 8'd22;
      #20
        			
      $finish;
    end
endmodule

dump.vcd
$date
	Wed Mar 24 11:09:54 2021
$end
$version
	Icarus Verilog
$end
$timescale
	1s
$end
$scope module tb $end
$scope module c1 $end
$var wire 8 ! addr [7:0] $end
$var wire 1 " clk $end
$var wire 8 # out [7:0] $end
$var wire 1 $ rst $end
$var integer 32 % i [31:0] $end
$var reg 8 & op [7:0] $end
$var reg 8 ' valid [0:7] $end
$upscope $end
$upscope $end
$enddefinitions $end
#0
$dumpvars
b0 '
b0 &
b1000 %
0$
b0 #
0"
bx !
$end
#5
bx &
bx #
1"
#10
0"
#15
1"
#20
0"
#25
1"
#30
0"
#35
1"
#40
0"
#45
1"
#50
0"
b10110 !
1$
#55
b1000 '
b10110 &
b10110 #
1"
#60
0"
#65
1"
#70
0"
b11000 !
#75
b10001000 '
b11000 &
b11000 #
1"
#80
0"
#85
1"
#90
0"
b11010 !
#95
b10001100 '
b11010 &
b11010 #
1"
#100
0"
#105
1"
#110
0"
b10110 !
#115
b10110 &
b10110 #
1"
#120
0"
#125
1"
#130
0"
b11101 !
#135
b10101100 '
b11101 &
b11101 #
1"
#140
0"
#145
1"
#150
0"
b11110 !
#155
b10101100 '
b11110 &
b11110 #
1"
#160
0"
#165
1"
#170
0"
b10110 !
#175
b10110 &
b10110 #
1"
